{
  "version": 1,
  "nextEID": 5,
  "mappings": [
    {
      "eid": 1,
      "canonical": "Mira",
      "normalizedKey": "mira",
      "created_at": "2025-11-10T04:26:11.912Z",
      "last_seen": "2025-11-10T04:26:11.912Z",
      "occurrence_count": 1
    },
    {
      "eid": 2,
      "canonical": "that she",
      "normalizedKey": "that she",
      "created_at": "2025-11-10T04:26:11.913Z",
      "last_seen": "2025-11-10T04:26:11.913Z",
      "occurrence_count": 1
    },
    {
      "eid": 3,
      "canonical": "Aria",
      "normalizedKey": "aria",
      "created_at": "2025-11-10T04:26:11.913Z",
      "last_seen": "2025-11-10T04:26:11.913Z",
      "occurrence_count": 1
    },
    {
      "eid": 4,
      "canonical": "Elias",
      "normalizedKey": "elias",
      "created_at": "2025-11-10T04:26:11.913Z",
      "last_seen": "2025-11-10T04:26:11.913Z",
      "occurrence_count": 1
    }
  ],
  "metadata": {
    "total_entities": 4,
    "last_updated": "2025-11-10T04:26:28.653Z"
  }
}